./.gitignore
./PKG-INFO
./README.md
./cli.py
./csv_metadata_format.md
./pyproject.toml
./requirements.txt
./server.py
./test_execution.py
./test_generate_barchart.py
./test_generate_pyecharts.py
./test_metadata.py
./.idea/.gitignore
./.idea/vcs.xml
./.idea/workspace.xml
./core/config.py
./core/data_types.py
./core/execution.py
./core/metadata.py
./core/visualization.py
./core/chart_generators/__init__.py
./core/chart_generators/bar.py
./core/chart_generators/base.py
./core/chart_generators/line.py
./core/chart_generators/pie.py
./core/chart_generators/templates/bar_template.html
./core/chart_generators/templates/line_template.html
./core/chart_generators/templates/pie_template.html
./logs/mcp_server.log
./logs/memory_20250710_133553.log
./logs/metadata_20250710_133553.log
iflow_mcp_pandas_mcp_server-0.1.0.dist-info/METADATA
iflow_mcp_pandas_mcp_server-0.1.0.dist-info/WHEEL
iflow_mcp_pandas_mcp_server-0.1.0.dist-info/entry_points.txt
iflow_mcp_pandas_mcp_server-0.1.0.dist-info/RECORD
