Metadata-Version: 2.4
Name: iflow-mcp_pandas-mcp-server
Version: 0.1.0
Summary: A comprehensive Model Context Protocol (MCP) server that enables LLMs to execute pandas code through a standardized workflow for data analysis and visualization.
Requires-Python: >=3.8
Requires-Dist: chardet>=5.0.0
Requires-Dist: fastmcp>=1.0.0
Requires-Dist: pandas>=2.0.0
Requires-Dist: psutil>=5.9.0
Provides-Extra: dev
Requires-Dist: pytest>=7.0.0; extra == 'dev'
